README.md
setup.py
oms/__init__.py
oms/api.py
oms/comm.py
oms/product.py
oms/stock.py
sf_oms_sdk.egg-info/PKG-INFO
sf_oms_sdk.egg-info/SOURCES.txt
sf_oms_sdk.egg-info/dependency_links.txt
sf_oms_sdk.egg-info/requires.txt
sf_oms_sdk.egg-info/top_level.txt
sf_oms_sdk.egg-info/zip-safe
tests/__init__.py
tests/test_comm.py