Metadata-Version: 2.1
Name: sf-oms-sdk
Version: 0.0.1
Summary: Shunfeng OMS Python SDK
Home-page: https://github.com/block-cat/sf-oms-sdk
Author: blackcat
Author-email: kfx2007@163.com
License: GNU
Keywords: s,f, ,s,d,k
Platform: UNKNOWN
Classifier: License :: OSI Approved :: GNU Affero General Public License v3
Classifier: Programming Language :: Python
Classifier: Operating System :: OS Independent
Classifier: Topic :: Scientific/Engineering :: Astronomy
Classifier: Topic :: Scientific/Engineering :: GIS
Classifier: Topic :: Scientific/Engineering :: Mathematics
Classifier: Intended Audience :: Science/Research
Classifier: Intended Audience :: Developers
Classifier: Intended Audience :: Information Technology
